polyhymnia/__init__.py
polyhymnia/_logger.py
polyhymnia/runserver.py
polyhymnia/serializers.py
polyhymnia/settings.py
polyhymnia/version.py
polyhymnia/data/simbert_v2_small.zip
polyhymnia/data/stopwords/README.md
polyhymnia/data/stopwords/baidu_stopwords.txt
polyhymnia/data/stopwords/cn_stopwords.txt
polyhymnia/data/stopwords/hit_stopwords.txt
polyhymnia/data/stopwords/scu_stopwords.txt
polyhymnia/decorators/__init__.py
polyhymnia/decorators/json.py
polyhymnia/decorators/param_check.py
polyhymnia/impl/__init__.py
polyhymnia/impl/simbert.py
polyhymnia/methods/__init__.py
polyhymnia/methods/noising/__init__.py
polyhymnia/methods/noising/deletion.py
polyhymnia/methods/noising/insertion.py
polyhymnia/methods/noising/substitution.py
polyhymnia/methods/noising/swapping.py
polyhymnia/methods/noising/stacking/__init__.py
polyhymnia/methods/noising/stacking/eda.py
polyhymnia/methods/paraphrasing/__init__.py
polyhymnia/methods/paraphrasing/generation/__init__.py
polyhymnia/methods/paraphrasing/generation/simbert.py
polyhymnia/methods/paraphrasing/translation/__init__.py
polyhymnia/methods/paraphrasing/translation/baidu.py
polyhymnia/methods/sampling/__init__.py
polyhymnia/utils/__init__.py
polyhymnia/utils/stop_words.py
polyhymnia/utils/synonyms.py
polyhymnia-1.0.0.dist-info/LICENSE
polyhymnia-1.0.0.dist-info/METADATA
polyhymnia-1.0.0.dist-info/WHEEL
polyhymnia-1.0.0.dist-info/top_level.txt
polyhymnia-1.0.0.dist-info/RECORD
