Metadata-Version: 2.1
Name: polyhymnia
Version: 1.0.0
Summary: Polyhymnia: Natual Chinese Data Augmentation
Home-page: https://github.com/luoy2/polyhymnia.git
Author: yikang
Author-email: luoy2@hotmail.com
License: Apache License 2.0
Keywords: corpus,NLU,NLP
Platform: UNKNOWN
Requires-Python: >=3.6
License-File: LICENSE
Requires-Dist: bert4keras (>=0.10.6)
Requires-Dist: synonyms (>=3.10.2)
Requires-Dist: scipy (>=1.7.1)
Requires-Dist: retry (>=0.9.2)
Requires-Dist: jieba (>=0.42.0)
Requires-Dist: zhon (>=1.1.5)
Requires-Dist: requests (>=2.24.0)
Requires-Dist: tensorflow (>=2.1.0)
